claim_ai_quality/__init__.py
claim_ai_quality/admin.py
claim_ai_quality/apps.py
claim_ai_quality/event_based_evaluation.py
claim_ai_quality/gql_mutations.py
claim_ai_quality/models.py
claim_ai_quality/report.py
claim_ai_quality/report_template.py
claim_ai_quality/schema.py
claim_ai_quality/services.py
claim_ai_quality/signals.py
claim_ai_quality/tasks.py
claim_ai_quality/temp_data.py
claim_ai_quality/urls.py
claim_ai_quality/utils.py
claim_ai_quality/views.py
claim_ai_quality/ai_evaluation/__init__.py
claim_ai_quality/ai_evaluation/integrated_evaluation_organizer.py
claim_ai_quality/ai_evaluation/mutation_evaluation.py
claim_ai_quality/ai_evaluation/rest_organizer.py
claim_ai_quality/ai_evaluation/websocket.py
claim_ai_quality/ai_evaluation/_rest_api/__init__.py
claim_ai_quality/ai_evaluation/_rest_api/eligible_claims_evaluation.py
claim_ai_quality/communication_interface/__init__.py
claim_ai_quality/communication_interface/rest_api/__init__.py
claim_ai_quality/communication_interface/rest_api/response_handler.py
claim_ai_quality/communication_interface/rest_api/restCommunicationInterface.py
claim_ai_quality/communication_interface/rest_api/rest_client.py
claim_ai_quality/communication_interface/websocket/__init__.py
claim_ai_quality/communication_interface/websocket/aiWebsocketClient.py
claim_ai_quality/communication_interface/websocket/fhirWebsocket.py
claim_ai_quality/communication_interface/websocket/response_dispatcher.py
claim_ai_quality/communication_interface/websocket/websocketCommunicationInterface.py
claim_ai_quality/fhir/__init__.py
claim_ai_quality/fhir/_claim_response_converter.py
claim_ai_quality/fhir/fhirConverter.py
claim_ai_quality/migrations/0001_initial_migration.py
claim_ai_quality/migrations/0002_claimaiqualitymutation.py
claim_ai_quality/migrations/0003_misclassification_report_role_right.py
claim_ai_quality/migrations/0004_claimbundleevaluationresult_historicalclaimbundleevaluationresult.py
openimis_be_claim_ai_quality-2.0.0.dist-info/LICENSE
openimis_be_claim_ai_quality-2.0.0.dist-info/METADATA
openimis_be_claim_ai_quality-2.0.0.dist-info/WHEEL
openimis_be_claim_ai_quality-2.0.0.dist-info/top_level.txt
openimis_be_claim_ai_quality-2.0.0.dist-info/RECORD
