Metadata-Version: 2.1
Name: openimis-be-claim-ai-quality
Version: 2.0.0
Summary: The openIMIS Backend Claim AI Quality reference module.
Home-page: https://openimis.org/
Author: Damian Borowiecki
Author-email: dborowiecki@soldevelo.com
License: GNU AGPL v3
Platform: UNKNOWN
Classifier: Environment :: Web Environment
Classifier: Framework :: Django
Classifier: Framework :: Django :: 2.1
Classifier: Intended Audience :: Developers
Classifier: License :: OSI Approved :: GNU Affero General Public License v3
Classifier: Operating System :: OS Independent
Classifier: Programming Language :: Python
Classifier: Programming Language :: Python :: 3.6
Classifier: Programming Language :: Python :: 3.7
License-File: LICENSE
Requires-Dist: django
Requires-Dist: django-db-signals
Requires-Dist: djangorestframework
Requires-Dist: orjson
Requires-Dist: fhir.resources (>=6.2.0b3)
Requires-Dist: openimis-be-api-fhir-r4
